{
    "url": "https://en.wikipedia.org/wiki/OakNorth_Bank",
    "name": "OakNorth_Bank",
    "description": "OakNorth is a UK bank for small and medium sized companies that provides business and property loans. The bank lends between \u00a3500,000 to \u00a345m to businesses and property developers. Its loans have supported the development of 9,500 homes and creation of 11,000 jobs in the UK.",
    "metadata": {
        "0": {},
        "1": {},
        "2": {},
        "3": {},
        "4": {},
        "5": {}
    }
}